body_matrix/__init__.py
body_matrix/draw.py
body_matrix/export.py
body_matrix/infer.py
body_matrix/load.py
body_matrix/measure.py
body_matrix/process.py
body_matrix/score.py
body_matrix-0.4.4.dist-info/LICENSE
body_matrix-0.4.4.dist-info/METADATA
body_matrix-0.4.4.dist-info/WHEEL
body_matrix-0.4.4.dist-info/top_level.txt
body_matrix-0.4.4.dist-info/RECORD
