Metadata-Version: 2.1
Name: body_matrix
Version: 0.4.4
Summary: Package to Calculate Human Body Measurements
Author-email: Hoang Do <hoang.do.2102@gmail.com>
Project-URL: Homepage, https://github.com/akando42/body_matrix
Project-URL: Bug Tracker, https://github.com/akando42/body_matrix/issues
Classifier: Programming Language :: Python :: 3
Classifier: License :: OSI Approved :: MIT License
Classifier: Operating System :: OS Independent
Requires-Python: >=3.7
License-File: LICENSE
